{"user_agents":{"a81297fcb3d2a82e":"Mozilla/5.0 (Macintosh; Intel Mac OS X 10_10_5) AppleWebKit/537.36 (KHTML, like Gecko) Chrome/58.0.3029.110 Safari/537.36","presenter":"Mozilla/5.0 (Macintosh; Intel Mac OS X 10_10_5) AppleWebKit/537.36 (KHTML, like Gecko) Chrome/58.0.3029.110 Safari/537.36"},"pageviews":{"Introduction/01":{"a81297fcb3d2a82e":[{"elapsed":2.261,"timestamp":1494648637,"presenter":null}]},"DL4J_overview/README":{"a81297fcb3d2a82e":[{"elapsed":1.16,"timestamp":1494648639,"presenter":null},{"elapsed":2.567,"timestamp":1494649292,"presenter":null},{"elapsed":1.312,"timestamp":1494650026,"presenter":null},{"elapsed":1.865,"timestamp":1494650567,"presenter":null},{"elapsed":1.585,"timestamp":1494653119,"presenter":null},{"elapsed":1.848,"timestamp":1494653124,"presenter":null},{"elapsed":1.144,"timestamp":1494653126,"presenter":null},{"elapsed":1.75,"timestamp":1494681650,"presenter":null},{"elapsed":3.794,"timestamp":1494681658,"presenter":null}]},"DL4J_overview/DataVec:1":{"a81297fcb3d2a82e":[{"elapsed":1.128,"timestamp":1494648642,"presenter":null},{"elapsed":2.592,"timestamp":1494650046,"presenter":null},{"elapsed":2.168,"timestamp":1494650049,"presenter":null},{"elapsed":6.864,"timestamp":1494681772,"presenter":null},{"elapsed":3.424,"timestamp":1494681777,"presenter":null}],"presenter":[{"elapsed":2.658,"timestamp":1494693311,"presenter":"DL4J_overview/DataVec:1"},{"elapsed":1.463,"timestamp":1494693313,"presenter":"DL4J_overview/DataVec:1"},{"elapsed":8.399,"timestamp":1494696112,"presenter":"Introduction/01:1"}]},"Introduction/01:2":{"a81297fcb3d2a82e":[{"elapsed":4.434,"timestamp":1494648914,"presenter":null},{"elapsed":2.762,"timestamp":1494649282,"presenter":null},{"elapsed":2.559,"timestamp":1494649286,"presenter":null},{"elapsed":1.862,"timestamp":1494649659,"presenter":null},{"elapsed":5.073,"timestamp":1494650556,"presenter":null},{"elapsed":1.643,"timestamp":1494653111,"presenter":null},{"elapsed":2.815,"timestamp":1494681490,"presenter":null},{"elapsed":2.759,"timestamp":1494689426,"presenter":null}],"presenter":[{"elapsed":3.864,"timestamp":1494695782,"presenter":"Introduction/01:2"},{"elapsed":10.4,"timestamp":1494695813,"presenter":"Introduction/01:1"}]},"Introduction/01:1":{"a81297fcb3d2a82e":[{"elapsed":5.465,"timestamp":1494648920,"presenter":null},{"elapsed":1.112,"timestamp":1494649283,"presenter":null},{"elapsed":11.02,"timestamp":1494649657,"presenter":null},{"elapsed":2.739,"timestamp":1494650551,"presenter":null},{"elapsed":2.972,"timestamp":1494689423,"presenter":null},{"elapsed":2.37,"timestamp":1495303139,"presenter":null}],"presenter":[{"elapsed":612.215,"timestamp":1494693297,"presenter":null},{"elapsed":1837.628,"timestamp":1494695795,"presenter":"Introduction/01:1"},{"elapsed":7.401,"timestamp":1494695803,"presenter":"Introduction/01:1"}]},"What_is_deep_learning/01":{"a81297fcb3d2a82e":[{"elapsed":3.066,"timestamp":1494649289,"presenter":null},{"elapsed":1.088,"timestamp":1494649660,"presenter":null}]},"What_is_deep_learning/01:1":{"a81297fcb3d2a82e":[{"elapsed":1.672,"timestamp":1494650020,"presenter":null},{"elapsed":1.503,"timestamp":1494650558,"presenter":null},{"elapsed":1.392,"timestamp":1494650561,"presenter":null}]},"What_is_deep_learning/01:2":{"a81297fcb3d2a82e":[{"elapsed":1.318,"timestamp":1494650021,"presenter":null},{"elapsed":2.208,"timestamp":1494653105,"presenter":null},{"elapsed":1.2,"timestamp":1494653113,"presenter":null},{"elapsed":2.253,"timestamp":1494681485,"presenter":null},{"elapsed":4.466,"timestamp":1494681495,"presenter":null},{"elapsed":2.344,"timestamp":1494689429,"presenter":null}],"presenter":[{"elapsed":2.056,"timestamp":1494693300,"presenter":"What_is_deep_learning/01:2"},{"elapsed":13.625,"timestamp":1494695827,"presenter":"Introduction/01:1"}]},"What_is_deep_learning/01:4":{"a81297fcb3d2a82e":[{"elapsed":2.185,"timestamp":1494650024,"presenter":null},{"elapsed":2.032,"timestamp":1494650565,"presenter":null},{"elapsed":3.04,"timestamp":1494653117,"presenter":null},{"elapsed":2.735,"timestamp":1494681649,"presenter":null},{"elapsed":4.366,"timestamp":1494689436,"presenter":null}],"presenter":[{"elapsed":1.555,"timestamp":1494693303,"presenter":"What_is_deep_learning/01:4"},{"elapsed":1262.288,"timestamp":1494693954,"presenter":"What_is_deep_learning/01:4"},{"elapsed":2441.075,"timestamp":1494695778,"presenter":"What_is_deep_learning/01:4"},{"elapsed":5.439,"timestamp":1494695965,"presenter":"Introduction/01:1"},{"elapsed":47.895,"timestamp":1494696023,"presenter":"Introduction/01:1"}]},"DL4J_overview/DeepLearning4J:2":{"a81297fcb3d2a82e":[{"elapsed":2.496,"timestamp":1494650029,"presenter":null},{"elapsed":1.376,"timestamp":1494650569,"presenter":null},{"elapsed":1.151,"timestamp":1494681755,"presenter":null},{"elapsed":4.737,"timestamp":1494681761,"presenter":null},{"elapsed":1.84,"timestamp":1494689439,"presenter":null}],"presenter":[{"elapsed":9.481,"timestamp":1494696036,"presenter":"Introduction/01:1"}]},"DL4J_overview/DeepLearning4J:3":{"a81297fcb3d2a82e":[{"elapsed":5.787,"timestamp":1494650035,"presenter":null},{"elapsed":1.095,"timestamp":1494650040,"presenter":null},{"elapsed":1.44,"timestamp":1494650572,"presenter":null},{"elapsed":4.355,"timestamp":1494681754,"presenter":null},{"elapsed":2.495,"timestamp":1494681764,"presenter":null}],"presenter":[{"elapsed":1.622,"timestamp":1494693307,"presenter":"DL4J_overview/DeepLearning4J:3"},{"elapsed":25.256,"timestamp":1494696061,"presenter":"Introduction/01:1"}]},"DL4J_overview/DeepLearning4J:4":{"a81297fcb3d2a82e":[{"elapsed":4.628,"timestamp":1494650039,"presenter":null},{"elapsed":1.761,"timestamp":1494650051,"presenter":null},{"elapsed":1.601,"timestamp":1494681765,"presenter":null}],"presenter":[{"elapsed":1.507,"timestamp":1494693308,"presenter":"DL4J_overview/DeepLearning4J:4"},{"elapsed":41.782,"timestamp":1494696103,"presenter":"Introduction/01:1"}]},"DL4J_overview/DataVec:2":{"a81297fcb3d2a82e":[{"elapsed":1.64,"timestamp":1494650053,"presenter":null},{"elapsed":1.016,"timestamp":1494653134,"presenter":null},{"elapsed":1.102,"timestamp":1494681773,"presenter":null}],"presenter":[{"elapsed":1.078,"timestamp":1494693312,"presenter":"DL4J_overview/DataVec:2"},{"elapsed":33.096,"timestamp":1494696145,"presenter":"Introduction/01:1"}]},"":{"a81297fcb3d2a82e":[{"elapsed":2.827,"timestamp":1494650545,"presenter":null}]},"DL4J_overview/ND4J:1":{"a81297fcb3d2a82e":[{"elapsed":1.945,"timestamp":1494650577,"presenter":null},{"elapsed":1.394,"timestamp":1494681898,"presenter":null}],"presenter":[{"elapsed":1.087,"timestamp":1494696172,"presenter":"Introduction/01:1"}]},"Paths_to_production/01":{"a81297fcb3d2a82e":[{"elapsed":3.656,"timestamp":1494650583,"presenter":null}]},"Some_examples/01":{"a81297fcb3d2a82e":[{"elapsed":19.441,"timestamp":1494650602,"presenter":null}]},"DL4J_overview/ND4J:3":{"a81297fcb3d2a82e":[{"elapsed":7.777,"timestamp":1494650613,"presenter":null},{"elapsed":1.66,"timestamp":1494682025,"presenter":null}],"presenter":[{"elapsed":1.561,"timestamp":1494693323,"presenter":"DL4J_overview/ND4J:3"},{"elapsed":31.663,"timestamp":1494696228,"presenter":"Introduction/01:1"}]},"Paths_to_production/01:2":{"a81297fcb3d2a82e":[{"elapsed":3.38,"timestamp":1494653026,"presenter":null},{"elapsed":4.12,"timestamp":1494653031,"presenter":null},{"elapsed":2.472,"timestamp":1494653097,"presenter":null},{"elapsed":1.206,"timestamp":1494653143,"presenter":null},{"elapsed":2.455,"timestamp":1494682029,"presenter":null},{"elapsed":1.8,"timestamp":1494683211,"presenter":null},{"elapsed":3.83,"timestamp":1495303151,"presenter":null}],"presenter":[{"elapsed":2.424,"timestamp":1494693327,"presenter":"Paths_to_production/01:2"},{"elapsed":157.108,"timestamp":1494696416,"presenter":"Introduction/01:1"},{"elapsed":27.937,"timestamp":1494696445,"presenter":"Introduction/01:1"}]},"Paths_to_production/01:3":{"a81297fcb3d2a82e":[{"elapsed":4.251,"timestamp":1494653094,"presenter":null},{"elapsed":1.024,"timestamp":1494653145,"presenter":null},{"elapsed":2.225,"timestamp":1494682031,"presenter":null},{"elapsed":1.799,"timestamp":1494683209,"presenter":null},{"elapsed":1.208,"timestamp":1494689448,"presenter":null},{"elapsed":2.209,"timestamp":1495303153,"presenter":null}],"presenter":[{"elapsed":2.072,"timestamp":1494693329,"presenter":"Paths_to_production/01:3"},{"elapsed":117.869,"timestamp":1494696563,"presenter":"Introduction/01:1"}]},"What_is_deep_learning/01:3":{"a81297fcb3d2a82e":[{"elapsed":1.008,"timestamp":1494653114,"presenter":null},{"elapsed":1.231,"timestamp":1494681496,"presenter":null},{"elapsed":1.953,"timestamp":1494689431,"presenter":null}],"presenter":[{"elapsed":1.092,"timestamp":1494693301,"presenter":"What_is_deep_learning/01:3"},{"elapsed":1.062,"timestamp":1494693955,"presenter":"What_is_deep_learning/01:4"},{"elapsed":132.308,"timestamp":1494695960,"presenter":"Introduction/01:1"},{"elapsed":10.377,"timestamp":1494695976,"presenter":"Introduction/01:1"}]},"DL4J_overview/DeepLearning4J:1":{"a81297fcb3d2a82e":[{"elapsed":1.408,"timestamp":1494653125,"presenter":null},{"elapsed":1.512,"timestamp":1494681652,"presenter":null},{"elapsed":1.048,"timestamp":1494681653,"presenter":null},{"elapsed":1.064,"timestamp":1494681756,"presenter":null},{"elapsed":1.656,"timestamp":1494689437,"presenter":null}],"presenter":[{"elapsed":1.048,"timestamp":1494693304,"presenter":"DL4J_overview/DeepLearning4J:1"},{"elapsed":3.27,"timestamp":1494696027,"presenter":"Introduction/01:1"}]},"DL4J_overview/DataVec:4":{"a81297fcb3d2a82e":[{"elapsed":1.968,"timestamp":1494653136,"presenter":null},{"elapsed":1.064,"timestamp":1494681778,"presenter":null},{"elapsed":1.176,"timestamp":1494689443,"presenter":null}],"presenter":[{"elapsed":2.608,"timestamp":1494693317,"presenter":"DL4J_overview/DataVec:4"},{"elapsed":21.36,"timestamp":1494696171,"presenter":"Introduction/01:1"}]},"DL4J_overview/ND4J:2":{"a81297fcb3d2a82e":[{"elapsed":3.232,"timestamp":1494653140,"presenter":null},{"elapsed":3.752,"timestamp":1494683219,"presenter":null}],"presenter":[{"elapsed":3.048,"timestamp":1494693321,"presenter":"DL4J_overview/ND4J:2"},{"elapsed":23.505,"timestamp":1494696196,"presenter":"Introduction/01:1"}]},"Paths_to_production/01:1":{"a81297fcb3d2a82e":[{"elapsed":1.01,"timestamp":1494653142,"presenter":null},{"elapsed":1.328,"timestamp":1494682027,"presenter":null},{"elapsed":9.025,"timestamp":1494683229,"presenter":null},{"elapsed":1.938,"timestamp":1495303157,"presenter":null},{"elapsed":1.184,"timestamp":1495303163,"presenter":null}],"presenter":[{"elapsed":10.472,"timestamp":1494696259,"presenter":"Introduction/01:1"}]},"Neural_networks_explained/01":{"a81297fcb3d2a82e":[{"elapsed":120.933,"timestamp":1494682020,"presenter":null}]},"Paths_to_production/01:4":{"a81297fcb3d2a82e":[{"elapsed":3.737,"timestamp":1494682035,"presenter":null},{"elapsed":1.55,"timestamp":1494682037,"presenter":null},{"elapsed":3.277,"timestamp":1494683207,"presenter":null},{"elapsed":1.072,"timestamp":1494683245,"presenter":null},{"elapsed":2.183,"timestamp":1494689450,"presenter":null},{"elapsed":1.218,"timestamp":1494689452,"presenter":null},{"elapsed":1.584,"timestamp":1495303155,"presenter":null},{"elapsed":1.856,"timestamp":1495303161,"presenter":null}],"presenter":[{"elapsed":1.88,"timestamp":1494693331,"presenter":"Paths_to_production/01:4"},{"elapsed":80.324,"timestamp":1494696643,"presenter":"Introduction/01:1"}]},"DL4J_overview/ND4J:4":{"a81297fcb3d2a82e":[{"elapsed":1.562,"timestamp":1494683213,"presenter":null},{"elapsed":2.289,"timestamp":1494689456,"presenter":null},{"elapsed":1.313,"timestamp":1495303164,"presenter":null}],"presenter":[{"elapsed":1.655,"timestamp":1494693324,"presenter":"DL4J_overview/ND4J:4"},{"elapsed":21.143,"timestamp":1494696249,"presenter":"Introduction/01:1"}]},"DL4J_overview/DataVec:3":{"presenter":[{"elapsed":5.191,"timestamp":1494696150,"presenter":"Introduction/01:1"}]}},"current":{"a81297fcb3d2a82e":["Paths_to_production/01:1",1495303164],"presenter":["Paths_to_production/01:4",1494696563]}}